objection_engine/MovieKit.py
objection_engine/__init__.py
objection_engine/ace_attorney_scene.py
objection_engine/beans/comment.py
objection_engine/beans/text.py
objection_engine/composers/compose_gavel_slam.py
objection_engine/composers/compose_verdict.py
objection_engine/font_constants.py
objection_engine/font_tools.py
objection_engine/gavel_slam.py
objection_engine/judge_verdict.py
objection_engine/loading.py
objection_engine/make_movie.py
objection_engine/math_helpers.py
objection_engine/parse_tags.py
objection_engine/renderer.py
objection_engine/tag_macros.py
objection_engine/testimony_indicator.py
objection_engine/utils.py
objection_engine-3.5.1.dist-info/LICENSE
objection_engine-3.5.1.dist-info/WHEEL
objection_engine-3.5.1.dist-info/METADATA
objection_engine-3.5.1.dist-info/RECORD
